groclake_setup_agent/__init__.py
groclake_setup_agent/setup_agent.py
groclake_setup_agent-0.1.5.dist-info/METADATA
groclake_setup_agent-0.1.5.dist-info/WHEEL
groclake_setup_agent-0.1.5.dist-info/entry_points.txt
groclake_setup_agent-0.1.5.dist-info/top_level.txt
groclake_setup_agent-0.1.5.dist-info/RECORD
